ran_exchange_rate/ExchangeRate.py
ran_exchange_rate/__init__.py
ran_exchange_rate-0.0.2.dist-info/LICENSE
ran_exchange_rate-0.0.2.dist-info/METADATA
ran_exchange_rate-0.0.2.dist-info/WHEEL
ran_exchange_rate-0.0.2.dist-info/top_level.txt
ran_exchange_rate-0.0.2.dist-info/RECORD
