Metadata-Version: 2.1
Name: ran-exchange-rate
Version: 0.0.2
Summary: Get the latest Exchange Rate, Base Currency: USD
Home-page: 
Author: ranyu
Author-email: wy176404@163.com
Classifier: Programming Language :: Python :: 3.6
Classifier: License :: OSI Approved :: MIT License
Classifier: Operating System :: OS Independent
License-File: LICENSE
